Metadata-Version: 2.1
Name: odoo14-addon-purchase_requisition_line_description
Version: 14.0.1.0.1.dev3
Summary: Extends the functionality of Purchase Agreements to show line description.
Home-page: https://github.com/OCA/purchase-workflow
Author: Camptocamp, Odoo Community Association (OCA)
Author-email: support@odoo-community.org
License: AGPL-3
Classifier: Programming Language :: Python
Classifier: Framework :: Odoo
Classifier: Framework :: Odoo :: 14.0
Classifier: License :: OSI Approved :: GNU Affero General Public License v3
Requires-Python: >=3.6
Requires-Dist: odoo<14.1dev,>=14.0a
